{"global":{
    "load_model_path":{"type":"string","description":"当继续训练时，指定模型路径","default":""},
    "use_parallel":{"type":"bool","description":"是否并行运行训练/测试","default":false},
    "use_gpu":{"type":"bool","description":"是否使用gpu","default":false},
    "num_of_device":{"type":"int","description":"使用的设备数","default":1},
    "model_path":{"type":"string","description":"预测使用模型路径","default":"File_Directory/models/model"}
  },
"dataset":{
    "dataset_path":{"type":"string", "description":"数据集路径","default":"File_Directory/dataset"},
    "examples_path":{"type":"string", "description":"examples缓存路径","default":"File_Directory/examples"},
    "batch_size":{"type":"int","description":"batch的大小","default":32},
    "max_seq_length":{"type":"int","description":"最长序列长度","default":512},
    "examples_type":{"type":"string","description":"读取examples文件类型","default":"example"},
    "examples_name":{"type":"string","description":"读取examples文件名","default":""},
    "examples_format":{"type":"string","description":"读取examples文件格式","default":"pickle"},
    "vocab_type":{"type":"string","description":"读取字典文件类型","default":"vocab"},
    "vocab_name":{"type":"string","description":"读取字典文件名","default":"vocab"},
    "vocab_format":{"type":"string","description":"读取字典文件格式","default":"txt"},
    "vocab_size":{"type":"int","description":"词表的大小","default":0},
    "do_lowercase":{"type":"bool","description":"是否进行对西文字符的处理","default":true},
    "is_save":{"type":"bool","description":"是否将tokenize后的结果保存下来","default":true},
    "is_mask":{"type":"bool","description":"是否进行mask覆盖","default":false},
    "is_predict":{"type":"bool","description":"是否为对测试集的处理","default":false},
    "shuffle":{"type":"bool","description":"是否对examples进行打乱","default":true},
    "shuffle_seed":{"type":"int","description":"打乱examples使用的seed","default":null}
  },
"build":{
    "num_labels":{"type":"int","description":"分类的类别数","default":3},
    "use_fp16":{"type":"bool","description":"是否使用浮点16位","default":false},
    "type_vocab_size":{"type":"int","description":"sententce_type的类型数","default":2},
    "hidden_size":{"type":"int","description":"embedding后向量的维数","default":384},
    "num_hidden_layers":{"type":"int","description":"内部encoder的层数","default":12},
    "num_attention_heads":{"type":"int","description":"attention_heads的数量","default":12},
    "hidden_act":{"type":"string","description":"激活函数的名称","default":"relu"},
    "hidden_dropout_prob":{"type":"float","description":"除attention参数外的dropout率","default":0},
    "attention_dropout_prob":{"type":"float","description":"attention参数的dropout率","default":0},
    "initializer_range":{"type":"float","description":"参数随机初始化时的标准差","default":0.02}
},
"train":{
    "max_epoch":{"type":"int","description":"最大训练epoch","default":20},
    "early_stopping":{"type":"bool","description":"是否采用早停策略","default":true},
    "early_stopping_threshold":{"type":"float","description":"性能增长比例小于阈值被判断为停滞","default":0.03},
    "early_stopping_stand_times":{"type":"int","description":"连续停滞超过几次停止训练","default":10},
    "base_learning_rate":{"type":"float","description":"基础学习率","default":0.0001},
    "learning_rate_strategy":{"type":"string","description":"学习率变化策略","default":"fixed"},
    "optimizer":{"type":"string","description":"优化器选择","default":"sgd"},
    "decay_step":{"type":"int","description":"学习率在这个步数范围内逐渐下降","default":10000},
    "decay_rate":{"type":"float","description":"学习率下降速率","default":0.5},
    "stair_decay":{"type":"bool","description":"学习率是否阶梯下降","default":false},
    "warm_up_step":{"type":"int","description":"warm_up的步数，0为不warm_up","default":4000},
    "start_learning_rate":{"type":"float","description":"初始学习率","default":1e-05},
    "end_learning_rate":{"type":"float","description":"最终学习率","default":1e-05},
    "momentum":{"type":"float","description":"动量","default":0.9},
    "use_nesterov":{"type":"bool","description":"是否赋能动量","default":false},
    "adagrad_epsilon":{"type":"float","description":"维持数值稳定性的浮点型值","default":1e-06},
    "adagrad_accumulator_value":{"type":"float","description":"moment累加器的初始值","default":0.0},
    "adam_beta1":{"type":"float","description":"一阶矩估计的指数衰减率","default":0.9},
    "adam_beta2":{"type":"float","description":"二阶矩估计的指数衰减率","default":0.999},
    "adam_epsilon":{"type":"float","description":"保持数值稳定性的短浮点类型值","default":1e-08},
    "snapshot_frequency":{"type":"int", "description":"每隔多少epoch保存一次训练快照", "default":10},
    "continue_train":{"type":"bool","description":"是否是接上一次训练，若为true必须指定load_model_path","default":false},
    "pretrained_model_path":{"type":"string", "description":"当是第一次训练时，指定预训练模型", "default":""}
},
"predict":{
  }
}
